rdafn/__init__.py
rdafn/analyze.py
rdafn/load.py
rdafn-1.2.0.dist-info/LICENSE
rdafn-1.2.0.dist-info/METADATA
rdafn-1.2.0.dist-info/WHEEL
rdafn-1.2.0.dist-info/top_level.txt
rdafn-1.2.0.dist-info/RECORD
