Metadata-Version: 2.1
Name: rdafn
Version: 1.2.0
Summary: Redistricting analytics for scoring ensembles of redistricting plans
Home-page: https://github.com/dra2020/rdafn
Author: alecramsay
Author-email: Alec Ramsay <a73cram5ay@gmail.com>
License: MIT
Project-URL: Homepage, https://github.com/dra2020/rdafn
Project-URL: Bug Tracker, https://github.com/dra2020/rdafn/issues
Classifier: Programming Language :: Python :: 3
Classifier: License :: OSI Approved :: MIT License
Classifier: Operating System :: OS Independent
Requires-Python: >=3.10
License-File: LICENSE
Requires-Dist: fiona
Requires-Dist: pytest
Requires-Dist: rdadata
Requires-Dist: rdapy
Requires-Dist: shapely
